{
  "id": "blinkin",
  "title": "Михаил Яковлевич Блинкин",
  "authorInfo": "Ординарный профессор НИУ ВШЭ,\nнаучный руководитель Института экономики\nтранспорта и транспортной политики,\nнаучный руководитель Факультета городского\nи регионального развития НИУ ВШЭ",
  "textSource": "",
  "image": "/images/reviews/blinkin.jpg",
  "thumbnail": "/imagesThumbs/reviews/blinkin.jpg",
  "imageCaption": "Михаил Яковлевич Блинкин (справа)",
  "text": "В 1962 году 80-летний в ту пору Корней Иванович Чуковский в беседе с писательницей Лидией Борисовной Либединской произнёс свою знаменитую фразу: «Когда я начинал печататься, я был самый молодой среди литераторов, а теперь я самый старый! В России надо жить долго – интересно!».\nУ Юрия Петровича Бочарова получилось примерно так же. В 1950-е годы, когда он начал печататься , Юрий Петрович был, бесспорно, одним из самых молодых (из числа публично известных) отечественных градостроителей. В 2010-2020-х, когда он продолжал регулярную публикацию своих статей (как всегда, безукоризненно аргументированных и политически острых !) в авторитетных профессиональных изданиях, Юрий Петрович выступал в роли старейшины нашего цеха.\nВ России, в самом деле, надо жить долго! А вот насколько это интересно, в сильнейшей степени зависит от личности. Юрию Петровичу, насколько я понимаю, всегда было интересно. Круг его интересов был необъятно широк: архитектор и историк архитектуры, художник-акварелист, урбанист во всех известных науке смыслах (“urban design”, “urban planning”, “land use regulations & zoning”…), транспортный планировщик (“urban transportation planner”), уникальный знаток теории и истории расселения и землепользования...\nГоворя о его профессиональных интересах, не могу не отметить, что профессор Бочаров первым в России обратил внимание на общепризнанное в мире разграничение между профессиями “architect”, “urban design”, “urban planning”, и, соответственно, на необходимость институализации этого разграничения.\n***\nС Юрием Петровичем Бочаровым меня познакомил мой старинный друг и коллега Александр Иванович Стрельников (1936 – 2021), который не был архитектором, но всю жизнь проработал бок о бок с архитекторами в отечественных, а иногда и в международных коллаборациях.  Саша был автором знаменитого доклада «Транспортное видение градостроительства» на VII Съезде Союза архитекторов России. На рубеже 1980-1990 годов Стрельников входил в состав правления Советского общества урбанистов, первым и последним президентом которого был Юрий Петрович.\nСтрельников подвёл меня к академику РААСН и представил: «Блинкин, известный учёный-транспортник». И здесь сразу проявился характер Юрия Петровича, который приводил меня в восторг все последующие годы нашего знакомства – он меня проэкзаменовал! Первый вопрос до сих пор помню: «В чём разница между лондонским и нью-йоркским правилами расчёта плотности застройки (FAR)?». Дальше последовали вопросы по всему полю землепользования-застройки-планировки-транспорта; цифры, факты, что происходит в Америке, что в русской провинции, что в Астане, что в Куритибе. У Юрия Петровича были совершенно энциклопедические познания, до старости лет фантастическая память, информация будто впечатывалась, весь мир стоял у него перед глазами. И вот он меня проэкзаменовал, констатировал, что всё, скажем так, неплохо; словом, признал причастность к профессиональному цеху. С тех пор мы стали регулярно общаться; к примеру, все последние годы мы с женой встречали Новый год в доме Бочаровых.\nБеседы с Юрием Петровичем позволили мне хоть как-то восполнить отсутствие регулярного образования в области архитектуры и градостроительства. Могу уверенно говорить о том, что мои познания в этой области во многом сформированы этим замечательным человеком. Неизбежные пробелы остаются, разумеется, на моей совести.\n***\nОсобенно активным было наше общение во времена обсуждения «лужковского» генплана Москвы. Юрий Петрович, упомянутый выше Александр Стрельников, историк архитектуры Алексей Алексеевич Клименко и я были, видимо, наиболее резкими и последовательными оппонентами этого документа. Время было ещё вполне подходящим для дискуссий, так что острые, подчас весьма нелицеприятные дискуссии с авторами этого проекта – главным архитектором Москвы тех лет Александром Викторовичем Кузьминым (1951 – 2019) и гендиректором Института Генплана Москвы Сергеем Борисовичем Ткаченко (1953 – 2023), велись на всех мыслимых площадках, от Общественной палаты РФ и всех подряд электронных и печатных СМИ, до Москомархитектуры и Центрального дома архитекторов в Гранатном переулке. Споры шли «по всему фронту» от исторического наследия и балансов/пропорций распределения городской территории, до состоятельности официальных прогнозов роста населения, автомобильного парка, структуры спроса на жильё и городские перемещения. Тональность разговора – предельно жёсткая по набору аргументов/ контаргументов, но абсолютно корректная по стилю.\nЧерез несколько лет после этих событий Кузьмин, в то время уже президент РААСН, в своём интервью к 90-летнему юбилею академика РААСН Бочарова произнёс знаковые слова: «Говорить о Юрии Петровиче Бочарове мне, с одной стороны, очень легко, потому что он является одним из лучших градостроителей России, наверное, середины XX – начала XXI века. С другой стороны, если вспомнить нашу совместную работу на протяжении многих лет, то мы чаще были по разные стороны баррикад, потому что я, как правило, был на стороне власти, а он старался быть на стороне правды. А это не всегда одно и то же».  Мне кажется, что эти слова много говорят о каждом из этих замечательных людей.\n***\nРяд работ Бочарова являются бесспорно классическими . К примеру, концептуальные соображения Юрия Петровича по поводу гибкой планировочной структуры города, по поводу зонирования промышленных районов и mix-use development, сформулированные еще в 1970-1980 годы, было бы весьма уместно включить в образовательный минимум сегодняшних магистров урбанистики.\nС городскими планировщиками, которые считают Юрия Петровича своим учителем или старшим товарищем, мне доводилось встречаться на пространстве от Владивостока до Волгограда, и от Астаны и Бишкека до Дербента.\nС городскими планировщиками, которые считают Юрия Петровича своим учителем или старшим товарищем, мне доводилось встречаться на пространстве от Владивостока до Волгограда, и от Астаны и Бишкека до Дербента.\nСреди «американских историй» Юрия Петровича меня особенно впечатлил рассказ о проекте ONECITY, придуманном гениальным визионером Уиллом Инсли и представленном публике в 1984 году в Музее Гуггенхайма на выставке его архитектурных рисунков. Рассказ Бочарова (который сам был изрядным мастером архитектурного рисунка!) об этом проекте и этой выставке скомпоновался у меня в памяти с эссе «Архетип пустого города» , написанном по поводу того же проекта Уилла Инсли всемирно известным математиком Юрием Ивановичем Маниным (1937 – 2023), которому я в студенческие годы сдавал экзамен по курсу алгебраической геометрии.\n***\nЗа долгие годы своей профессиональной карьеры Юрию Петровичу довелось побывать в роли архитектора, планировщика-практика, правительственного консультанта, международного чиновника, «научного генерала» , университетского профессора…  Во всех этих ролях он сохранял неизменное профессиональное и человеческое достоинство, готовность отстаивать собственную систему взглядов и ценностей, а также редкостное по нынешним временам сочетание толерантности и понимания рубежей, за которыми толерантность неуместна."
}